{
  "timestamp": "2025-11-20T09:03:07Z",
  "total_files_scanned": 3851,
  "duplicate_groups": 2,
  "total_wasted_bytes": 180,
  "total_wasted_mb": 0.0,
  "duplicates": [
    {
      "hash": "3d2989c1cc405c93dedd8236fd341655",
      "size": 36,
      "count": 6,
      "wasted_space": 180,
      "files": [
        "./tests/state/technician.json",
        "./tests/state/tenant.json",
        "./tests/state/vendor.json",
        "./tests/state/superadmin.json",
        "./tests/state/admin.json",
        "./tests/state/manager.json"
      ]
    },
    {
      "hash": "d41d8cd98f00b204e9800998ecf8427e",
      "size": 0,
      "count": 2,
      "wasted_space": 0,
      "files": [
        "./duplicate-detection-report.json",
        "./docs/archived/TODO_RESOLUTION_FINAL_SUMMARY.md"
      ]
    }
  ]
}
